[
    {
      "name": "Clark",
      "score": 345
    },
    {
      "name": "Clark",
      "score": 76
    },
    {
      "name": "Clark",
      "score": 362
    },
    {
      "name": "Harrison",
      "score": 23
    },
    {
      "name": "Harrison",
      "score": 23
    },
    {
      "name": "Kaine",
      "score": 32
    },
    {
      "name": "Kaine",
      "score": 322
    },
    {
      "name": "Kaine",
      "score": 32
    },
    {
      "name": "Kaine",
      "score": 324
    },
    {
      "name": "Kalem",
      "score": 323
    },
    {
      "name": "Max",
      "score": 336
    },
    {
      "name": "Harrison",
      "score": 543
    },
    {
      "name": "Harrison",
      "score": 232
    },
    {
      "name": "Max",
      "score": 32
    },
    {
      "name": "Max",
      "score": 1
    }
]